trytond/modules/calendar_classification/__init__.py
trytond/modules/calendar_classification/calendar_.py
trytond/modules/calendar_classification/tryton.cfg
trytond/modules/calendar_classification/locale/bg.po
trytond/modules/calendar_classification/locale/ca.po
trytond/modules/calendar_classification/locale/cs.po
trytond/modules/calendar_classification/locale/de.po
trytond/modules/calendar_classification/locale/es.po
trytond/modules/calendar_classification/locale/es_419.po
trytond/modules/calendar_classification/locale/fr.po
trytond/modules/calendar_classification/locale/hu_HU.po
trytond/modules/calendar_classification/locale/it_IT.po
trytond/modules/calendar_classification/locale/ja_JP.po
trytond/modules/calendar_classification/locale/lo.po
trytond/modules/calendar_classification/locale/lt.po
trytond/modules/calendar_classification/locale/nl.po
trytond/modules/calendar_classification/locale/pl.po
trytond/modules/calendar_classification/locale/pt_BR.po
trytond/modules/calendar_classification/locale/ru.po
trytond/modules/calendar_classification/locale/sl.po
trytond/modules/calendar_classification/locale/zh_CN.po
trytond_calendar_classification-4.2.0.dist-info/DESCRIPTION.rst
trytond_calendar_classification-4.2.0.dist-info/METADATA
trytond_calendar_classification-4.2.0.dist-info/RECORD
trytond_calendar_classification-4.2.0.dist-info/WHEEL
trytond_calendar_classification-4.2.0.dist-info/entry_points.txt
trytond_calendar_classification-4.2.0.dist-info/metadata.json
trytond_calendar_classification-4.2.0.dist-info/top_level.txt
